{
  "arch_name": "transformer_shallow",
  "dataset_name": "cifar10",
  "architecture_params": {
    "depth": 2,
    "width": 128,
    "num_params": 95000
  },
  "measurements": [
    {
      "step": 0,
      "loss": 2.4,
      "grad_norm": 2.1,
      "layer_metrics": {
        "layer_0": {
          "stable_rank": 0.5,
          "participation_ratio": 0.475,
          "effective_rank_90": 0.425,
          "nuclear_norm_ratio": 0.55
        }
      }
    },
    {
      "step": 5,
      "loss": 2.343212797665165,
      "grad_norm": 2.066942907643235,
      "layer_metrics": {
        "layer_0": {
          "stable_rank": 0.3877380224928486,
          "participation_ratio": 0.36835112136820614,
          "effective_rank_90": 0.3295773191189213,
          "nuclear_norm_ratio": 0.4265118247421335
        }
      }
    },
    {
      "step": 10,
      "loss": 2.2878276763516423,
      "grad_norm": 2.034432200964012,
      "layer_metrics": {
        "layer_0": {
          "stable_rank": 0.37061926681952617,
          "participation_ratio": 0.35208830347854986,
          "effective_rank_90": 0.31502637679659723,
          "nuclear_norm_ratio": 0.4076811935014788
        }
      }
    },
    {
      "step": 15,
      "loss": 2.2338100185556713,
      "grad_norm": 2.002458849001428,
      "layer_metrics": {
        "layer_0": {
          "stable_rank": 0.38904864875042594,
          "participation_ratio": 0.3695962163129046,
          "effective_rank_90": 0.33069135143786205,
          "nuclear_norm_ratio": 0.4279535136254686
        }
      }
    },
    {
      "step": 20,
      "loss": 2.181126061482707,
      "grad_norm": 1.9710139700632356,
      "layer_metrics": {
        "layer_0": {
          "stable_rank": 0.17168552054470254,
          "participation_ratio": 0.1631012445174674,
          "effective_rank_90": 0.14593269246299714,
          "nuclear_norm_ratio": 0.1888540725991728
        }
      }
    },
    {
      "step": 25,
      "loss": 2.129742875944569,
      "grad_norm": 1.9400888292586467,
      "layer_metrics": {
        "layer_0": {
          "stable_rank": 0.17463743342930696,
          "participation_ratio": 0.1659055617578416,
          "effective_rank_90": 0.14844181841491091,
          "nuclear_norm_ratio": 0.19210117677223768
        }
      }
    },
    {
      "step": 30,
      "loss": 2.079628345777633,
      "grad_norm": 1.9096748360719191,
      "layer_metrics": {
        "layer_0": {
          "stable_rank": 0.02372031060327484,
          "participation_ratio": 0.022534295073111096,
          "effective_rank_90": 0.020162264012783614,
          "nuclear_norm_ratio": 0.026092341663602327
        }
      }
    },
    {
      "step": 35,
      "loss": 2.030751147769177,
      "grad_norm": 1.8797635419760477,
      "layer_metrics": {
        "layer_0": {
          "stable_rank": 0.09069834850935019,
          "participation_ratio": 0.08616343108388268,
          "effective_rank_90": 0.07709359623294766,
          "nuclear_norm_ratio": 0.09976818336028521
        }
      }
    },
    {
      "step": 40,
      "loss": 1.9830807320793582,
      "grad_norm": 1.850346638085895,
      "layer_metrics": {
        "layer_0": {
          "stable_rank": 0.2999019057862178,
          "participation_ratio": 0.28490681049690686,
          "effective_rank_90": 0.2549166199182851,
          "nuclear_norm_ratio": 0.32989209636483957
        }
      }
    },
    {
      "step": 45,
      "loss": 1.9365873031465672,
      "grad_norm": 1.8214159528501157,
      "layer_metrics": {
        "layer_0": {
          "stable_rank": 0.2838179573389015,
          "participation_ratio": 0.2696270594719564,
          "effective_rank_90": 0.2412452637380663,
          "nuclear_norm_ratio": 0.3121997530727917
        }
      }
    },
    {
      "step": 50,
      "loss": 1.8912418010642311,
      "grad_norm": 1.7929634497812283,
      "layer_metrics": {
        "layer_0": {
          "stable_rank": 0.5953355146871692,
          "participation_ratio": 0.5655687389528107,
          "effective_rank_90": 0.5060351874840938,
          "nuclear_norm_ratio": 0.6548690661558861
        }
      }
    },
    {
      "step": 55,
      "loss": 1.8470158834174275,
      "grad_norm": 1.7649812252232056,
      "layer_metrics": {
        "layer_0": {
          "stable_rank": 0.5999972596053718,
          "participation_ratio": 0.5699973966251032,
          "effective_rank_90": 0.509997670664566,
          "nuclear_norm_ratio": 0.659996985565909
        }
      }
    },
    {
      "step": 60,
      "loss": 1.803881907567951,
      "grad_norm": 1.7374615061559637,
      "layer_metrics": {
        "layer_0": {
          "stable_rank": 0.7105745114571906,
          "participation_ratio": 0.6750457858843311,
          "effective_rank_90": 0.603988334738612,
          "nuclear_norm_ratio": 0.7816319626029098
        }
      }
    },
    {
      "step": 65,
      "loss": 1.7618129133767662,
      "grad_norm": 1.7103966480361412,
      "layer_metrics": {
        "layer_0": {
          "stable_rank": 0.8047149470964206,
          "participation_ratio": 0.7644791997415995,
          "effective_rank_90": 0.6840077050319574,
          "nuclear_norm_ratio": 0.8851864418060627
        }
      }
    },
    {
      "step": 70,
      "loss": 1.720782606353041,
      "grad_norm": 1.6837791326735634,
      "layer_metrics": {
        "layer_0": {
          "stable_rank": 0.8647320615950743,
          "participation_ratio": 0.8214954585153206,
          "effective_rank_90": 0.7350222523558132,
          "nuclear_norm_ratio": 0.9512052677545818
        }
      }
    },
    {
      "step": 75,
      "loss": 1.680765341219236,
      "grad_norm": 1.6576015661428098,
      "layer_metrics": {
        "layer_0": {
          "stable_rank": 0.9624861474004467,
          "participation_ratio": 0.9143618400304243,
          "effective_rank_90": 0.8181132252903797,
          "nuclear_norm_ratio": 1.0587347621404914
        }
      }
    },
    {
      "step": 80,
      "loss": 1.6417361058819704,
      "grad_norm": 1.6318566767292975,
      "layer_metrics": {
        "layer_0": {
          "stable_rank": 1.255278954461275,
          "participation_ratio": 1.1925150067382113,
          "effective_rank_90": 1.0669871112920837,
          "nuclear_norm_ratio": 1.3808068499074027
        }
      }
    },
    {
      "step": 85,
      "loss": 1.6036705057986487,
      "grad_norm": 1.6065373129093137,
      "layer_metrics": {
        "layer_0": {
          "stable_rank": 1.2474477546552065,
          "participation_ratio": 1.185075366922446,
          "effective_rank_90": 1.0603305914569254,
          "nuclear_norm_ratio": 1.3721925301207272
        }
      }
    },
    {
      "step": 90,
      "loss": 1.5665447487300785,
      "grad_norm": 1.5816364413634358,
      "layer_metrics": {
        "layer_0": {
          "stable_rank": 1.2998420840105758,
          "participation_ratio": 1.234849979810047,
          "effective_rank_90": 1.1048657714089893,
          "nuclear_norm_ratio": 1.4298262924116334
        }
      }
    },
    {
      "step": 95,
      "loss": 1.5303356298695463,
      "grad_norm": 1.557147145022786,
      "layer_metrics": {
        "layer_0": {
          "stable_rank": 1.5096207543395959,
          "participation_ratio": 1.434139716622616,
          "effective_rank_90": 1.2831776411886564,
          "nuclear_norm_ratio": 1.6605828297735556
        }
      }
    },
    {
      "step": 100,
      "loss": 1.495020517339057,
      "grad_norm": 1.5330626211475786,
      "layer_metrics": {
        "layer_0": {
          "stable_rank": 1.4862859575449752,
          "participation_ratio": 1.4119716596677263,
          "effective_rank_90": 1.2633430639132288,
          "nuclear_norm_ratio": 1.6349145532994729
        }
      }
    },
    {
      "step": 105,
      "loss": 1.4605773380436746,
      "grad_norm": 1.509376179437427,
      "layer_metrics": {
        "layer_0": {
          "stable_rank": 1.5110084527180685,
          "participation_ratio": 1.435458030082165,
          "effective_rank_90": 1.284357184810358,
          "nuclear_norm_ratio": 1.6621092979898755
        }
      }
    },
    {
      "step": 110,
      "loss": 1.4269845638751193,
      "grad_norm": 1.4860812401728831,
      "layer_metrics": {
        "layer_0": {
          "stable_rank": 1.6547701482051287,
          "participation_ratio": 1.5720316407948722,
          "effective_rank_90": 1.4065546259743593,
          "nuclear_norm_ratio": 1.8202471630256416
        }
      }
    },
    {
      "step": 115,
      "loss": 1.394221198255998,
      "grad_norm": 1.4631713323876958,
      "layer_metrics": {
        "layer_0": {
          "stable_rank": 1.5749945335180873,
          "participation_ratio": 1.4962448068421828,
          "effective_rank_90": 1.3387453534903742,
          "nuclear_norm_ratio": 1.732493986869896
        }
      }
    },
    {
      "step": 120,
      "loss": 1.3622667630162606,
      "grad_norm": 1.4406400920712787,
      "layer_metrics": {
        "layer_0": {
          "stable_rank": 1.3343878768894464,
          "participation_ratio": 1.267668483044974,
          "effective_rank_90": 1.1342296953560294,
          "nuclear_norm_ratio": 1.467826664578391
        }
      }
    },
    {
      "step": 125,
      "loss": 1.3311012855936777,
      "grad_norm": 1.4184812604008876,
      "layer_metrics": {
        "layer_0": {
          "stable_rank": 1.3839979778133074,
          "participation_ratio": 1.3147980789226419,
          "effective_rank_90": 1.1763982811413112,
          "nuclear_norm_ratio": 1.5223977755946383
        }
      }
    },
    {
      "step": 130,
      "loss": 1.3007052865503368,
      "grad_norm": 1.3966886820030195,
      "layer_metrics": {
        "layer_0": {
          "stable_rank": 1.6161197327125427,
          "participation_ratio": 1.5353137460769155,
          "effective_rank_90": 1.3737017728056613,
          "nuclear_norm_ratio": 1.7777317059837972
        }
      }
    },
    {
      "step": 135,
      "loss": 1.2710597673973631,
      "grad_norm": 1.3752563032435468,
      "layer_metrics": {
        "layer_0": {
          "stable_rank": 1.5238223234191064,
          "participation_ratio": 1.447631207248151,
          "effective_rank_90": 1.2952489749062404,
          "nuclear_norm_ratio": 1.6762045557610172
        }
      }
    },
    {
      "step": 140,
      "loss": 1.242146198720242,
      "grad_norm": 1.3541781705461122,
      "layer_metrics": {
        "layer_0": {
          "stable_rank": 1.4287848833406973,
          "participation_ratio": 1.3573456391736625,
          "effective_rank_90": 1.2144671508395928,
          "nuclear_norm_ratio": 1.5716633716747672
        }
      }
    },
    {
      "step": 145,
      "loss": 1.2139465085973338,
      "grad_norm": 1.3334484287383217,
      "layer_metrics": {
        "layer_0": {
          "stable_rank": 1.449475295997288,
          "participation_ratio": 1.3770015311974235,
          "effective_rank_90": 1.2320540015976948,
          "nuclear_norm_ratio": 1.594422825597017
        }
      }
    },
    {
      "step": 150,
      "loss": 1.1864430713043337,
      "grad_norm": 1.313061319425267,
      "layer_metrics": {
        "layer_0": {
          "stable_rank": 1.4726447905093296,
          "participation_ratio": 1.3990125509838631,
          "effective_rank_90": 1.2517480719329301,
          "nuclear_norm_ratio": 1.6199092695602626
        }
      }
    },
    {
      "step": 155,
      "loss": 1.1596186962976214,
      "grad_norm": 1.2930111793899368,
      "layer_metrics": {
        "layer_0": {
          "stable_rank": 1.5148255046592105,
          "participation_ratio": 1.4390842294262498,
          "effective_rank_90": 1.2876016789603288,
          "nuclear_norm_ratio": 1.6663080551251317
        }
      }
    },
    {
      "step": 160,
      "loss": 1.1334566174696097,
      "grad_norm": 1.2732924390200637,
      "layer_metrics": {
        "layer_0": {
          "stable_rank": 1.5244032101406724,
          "participation_ratio": 1.4481830496336388,
          "effective_rank_90": 1.2957427286195715,
          "nuclear_norm_ratio": 1.6768435311547398
        }
      }
    },
    {
      "step": 165,
      "loss": 1.1079404826693833,
      "grad_norm": 1.2538996207609734,
      "layer_metrics": {
        "layer_0": {
          "stable_rank": 1.5753312815821716,
          "participation_ratio": 1.496564717503063,
          "effective_rank_90": 1.339031589344846,
          "nuclear_norm_ratio": 1.732864409740389
        }
      }
    },
    {
      "step": 170,
      "loss": 1.0830543434820712,
      "grad_norm": 1.2348273375940078,
      "layer_metrics": {
        "layer_0": {
          "stable_rank": 1.4918479859567702,
          "participation_ratio": 1.4172555866589316,
          "effective_rank_90": 1.2680707880632547,
          "nuclear_norm_ratio": 1.6410327845524473
        }
      }
    },
    {
      "step": 175,
      "loss": 1.0587826452605693,
      "grad_norm": 1.2160702915400943,
      "layer_metrics": {
        "layer_0": {
          "stable_rank": 1.5494642496281792,
          "participation_ratio": 1.4719910371467702,
          "effective_rank_90": 1.3170446121839523,
          "nuclear_norm_ratio": 1.7044106745909973
        }
      }
    },
    {
      "step": 180,
      "loss": 1.035110217403378,
      "grad_norm": 1.1976232721880529,
      "layer_metrics": {
        "layer_0": {
          "stable_rank": 1.5420956162679766,
          "participation_ratio": 1.4649908354545778,
          "effective_rank_90": 1.3107812738277802,
          "nuclear_norm_ratio": 1.6963051778947744
        }
      }
    },
    {
      "step": 185,
      "loss": 1.0120222638724834,
      "grad_norm": 1.1794811552472253,
      "layer_metrics": {
        "layer_0": {
          "stable_rank": 1.5936234945198933,
          "participation_ratio": 1.5139423197938986,
          "effective_rank_90": 1.3545799703419092,
          "nuclear_norm_ratio": 1.7529858439718828
        }
      }
    },
    {
      "step": 190,
      "loss": 0.9895043539453527,
      "grad_norm": 1.161638901124028,
      "layer_metrics": {
        "layer_0": {
          "stable_rank": 1.6742508788458295,
          "participation_ratio": 1.590538334903538,
          "effective_rank_90": 1.423113247018955,
          "nuclear_norm_ratio": 1.8416759667304126
        }
      }
    },
    {
      "step": 195,
      "loss": 0.9675424131952609,
      "grad_norm": 1.1440915535220322,
      "layer_metrics": {
        "layer_0": {
          "stable_rank": 1.7177423232835776,
          "participation_ratio": 1.6318552071193986,
          "effective_rank_90": 1.4600809747910408,
          "nuclear_norm_ratio": 1.8895165556119355
        }
      }
    },
    {
      "step": 200,
      "loss": 0.9461227146943173,
      "grad_norm": 1.1268342380651841,
      "layer_metrics": {
        "layer_0": {
          "stable_rank": 1.7755378762559262,
          "participation_ratio": 1.6867609824431298,
          "effective_rank_90": 1.5092071948175372,
          "nuclear_norm_ratio": 1.953091663881519
        }
      }
    },
    {
      "step": 205,
      "loss": 0.9252318704336886,
      "grad_norm": 1.1098621609437795,
      "layer_metrics": {
        "layer_0": {
          "stable_rank": 1.8007095576533056,
          "participation_ratio": 1.7106740797706403,
          "effective_rank_90": 1.5306031240053097,
          "nuclear_norm_ratio": 1.9807805134186365
        }
      }
    },
    {
      "step": 210,
      "loss": 0.9048568229556572,
      "grad_norm": 1.0931706075828191,
      "layer_metrics": {
        "layer_0": {
          "stable_rank": 1.633760756174087,
          "participation_ratio": 1.5520727183653826,
          "effective_rank_90": 1.3886966427479739,
          "nuclear_norm_ratio": 1.7971368317914957
        }
      }
    },
    {
      "step": 215,
      "loss": 0.8849848371922855,
      "grad_norm": 1.0767549413323743,
      "layer_metrics": {
        "layer_0": {
          "stable_rank": 1.8199779337747541,
          "participation_ratio": 1.7289790370860163,
          "effective_rank_90": 1.546981243708541,
          "nuclear_norm_ratio": 2.00197572715223
        }
      }
    },
    {
      "step": 220,
      "loss": 0.8656034925055829,
      "grad_norm": 1.060610602179599,
      "layer_metrics": {
        "layer_0": {
          "stable_rank": 1.9262779029501802,
          "participation_ratio": 1.829964007802671,
          "effective_rank_90": 1.6373362175076531,
          "nuclear_norm_ratio": 2.1189056932451984
        }
      }
    },
    {
      "step": 225,
      "loss": 0.8467006749242043,
      "grad_norm": 1.0447331054820295,
      "layer_metrics": {
        "layer_0": {
          "stable_rank": 2.051043449201935,
          "participation_ratio": 1.9484912767418383,
          "effective_rank_90": 1.7433869318216448,
          "nuclear_norm_ratio": 2.256147794122129
        }
      }
    },
    {
      "step": 230,
      "loss": 0.8282645695718224,
      "grad_norm": 1.029118040721823,
      "layer_metrics": {
        "layer_0": {
          "stable_rank": 2.0083335139643683,
          "participation_ratio": 1.9079168382661498,
          "effective_rank_90": 1.7070834868697131,
          "nuclear_norm_ratio": 2.2091668653608054
        }
      }
    },
    {
      "step": 235,
      "loss": 0.8102836532824456,
      "grad_norm": 1.0137610702805842,
      "layer_metrics": {
        "layer_0": {
          "stable_rank": 2.1243956893199645,
          "participation_ratio": 2.0181759048539663,
          "effective_rank_90": 1.8057363359219698,
          "nuclear_norm_ratio": 2.336835258251961
        }
      }
    },
    {
      "step": 240,
      "loss": 0.7927466873980648,
      "grad_norm": 0.9986579282344431,
      "layer_metrics": {
        "layer_0": {
          "stable_rank": 2.3966456736038375,
          "participation_ratio": 2.2768133899236456,
          "effective_rank_90": 2.0371488225632617,
          "nuclear_norm_ratio": 2.6363102409642214
        }
      }
    },
    {
      "step": 245,
      "loss": 0.7756427107441253,
      "grad_norm": 0.9838044191690506,
      "layer_metrics": {
        "layer_0": {
          "stable_rank": 2.267527560768302,
          "participation_ratio": 2.1541511827298865,
          "effective_rank_90": 1.9273984266530566,
          "nuclear_norm_ratio": 2.494280316845132
        }
      }
    },
    {
      "step": 250,
      "loss": 0.7589610327784372,
      "grad_norm": 0.9691964170141564,
      "layer_metrics": {
        "layer_0": {
          "stable_rank": 2.370184864171975,
          "participation_ratio": 2.251675620963376,
          "effective_rank_90": 2.014657134546179,
          "nuclear_norm_ratio": 2.6072033505891725
        }
      }
    },
    {
      "step": 255,
      "loss": 0.7426912269092368,
      "grad_norm": 0.9548298638974533,
      "layer_metrics": {
        "layer_0": {
          "stable_rank": 2.345268837361885,
          "participation_ratio": 2.2280053954937906,
          "effective_rank_90": 1.9934785117576022,
          "nuclear_norm_ratio": 2.579795721098074
        }
      }
    },
    {
      "step": 260,
      "loss": 0.7268231239782289,
      "grad_norm": 0.9407007690173638,
      "layer_metrics": {
        "layer_0": {
          "stable_rank": 2.283195468871191,
          "participation_ratio": 2.169035695427631,
          "effective_rank_90": 1.9407161485405122,
          "nuclear_norm_ratio": 2.51151501575831
        }
      }
    },
    {
      "step": 265,
      "loss": 0.7113468059045311,
      "grad_norm": 0.9268052075344586,
      "layer_metrics": {
        "layer_0": {
          "stable_rank": 2.245144065820863,
          "participation_ratio": 2.1328868625298196,
          "effective_rank_90": 1.9083724559477333,
          "nuclear_norm_ratio": 2.469658472402949
        }
      }
    },
    {
      "step": 270,
      "loss": 0.6962525994855504,
      "grad_norm": 0.9131393194811982,
      "layer_metrics": {
        "layer_0": {
          "stable_rank": 2.2543177920287434,
          "participation_ratio": 2.1416019024273063,
          "effective_rank_90": 1.916170123224432,
          "nuclear_norm_ratio": 2.479749571231618
        }
      }
    },
    {
      "step": 275,
      "loss": 0.6815310703509168,
      "grad_norm": 0.8996993086896947,
      "layer_metrics": {
        "layer_0": {
          "stable_rank": 2.356366174312704,
          "participation_ratio": 2.2385478655970683,
          "effective_rank_90": 2.0029112481657982,
          "nuclear_norm_ratio": 2.5920027917439743
        }
      }
    },
    {
      "step": 280,
      "loss": 0.6671730170656949,
      "grad_norm": 0.8864814417371965,
      "layer_metrics": {
        "layer_0": {
          "stable_rank": 2.4565865682789836,
          "participation_ratio": 2.3337572398650344,
          "effective_rank_90": 2.088098583037136,
          "nuclear_norm_ratio": 2.702245225106882
        }
      }
    },
    {
      "step": 285,
      "loss": 0.6531694653791869,
      "grad_norm": 0.8734820469090024,
      "layer_metrics": {
        "layer_0": {
          "stable_rank": 2.460083254744828,
          "participation_ratio": 2.3370790920075866,
          "effective_rank_90": 2.091070766533104,
          "nuclear_norm_ratio": 2.706091580219311
        }
      }
    },
    {
      "step": 290,
      "loss": 0.6395116626157346,
      "grad_norm": 0.8606975131785171,
      "layer_metrics": {
        "layer_0": {
          "stable_rank": 2.4565799975970024,
          "participation_ratio": 2.333750997717152,
          "effective_rank_90": 2.088092997957452,
          "nuclear_norm_ratio": 2.702237997356703
        }
      }
    },
    {
      "step": 295,
      "loss": 0.6261910722040115,
      "grad_norm": 0.8481242892041653,
      "layer_metrics": {
        "layer_0": {
          "stable_rank": 2.3922878753316867,
          "participation_ratio": 2.272673481565102,
          "effective_rank_90": 2.0334446940319335,
          "nuclear_norm_ratio": 2.6315166628648554
        }
      }
    },
    {
      "step": 300,
      "loss": 0.6131993683413886,
      "grad_norm": 0.8357588823428846,
      "layer_metrics": {
        "layer_0": {
          "stable_rank": 2.3991340129096552,
          "participation_ratio": 2.2791773122641725,
          "effective_rank_90": 2.0392639109732067,
          "nuclear_norm_ratio": 2.639047414200621
        }
      }
    },
    {
      "step": 305,
      "loss": 0.6005284307900356,
      "grad_norm": 0.8235978576799252,
      "layer_metrics": {
        "layer_0": {
          "stable_rank": 2.5354729488006775,
          "participation_ratio": 2.4086993013606435,
          "effective_rank_90": 2.155152006480576,
          "nuclear_norm_ratio": 2.7890202436807456
        }
      }
    },
    {
      "step": 310,
      "loss": 0.588170339801509,
      "grad_norm": 0.8116378370746837,
      "layer_metrics": {
        "layer_0": {
          "stable_rank": 2.7589967587112247,
          "participation_ratio": 2.6210469207756635,
          "effective_rank_90": 2.345147244904541,
          "nuclear_norm_ratio": 3.0348964345823473
        }
      }
    },
    {
      "step": 315,
      "loss": 0.5761173711666511,
      "grad_norm": 0.7998754982223106,
      "layer_metrics": {
        "layer_0": {
          "stable_rank": 2.700418748515221,
          "participation_ratio": 2.5653978110894595,
          "effective_rank_90": 2.2953559362379377,
          "nuclear_norm_ratio": 2.970460623366743
        }
      }
    },
    {
      "step": 320,
      "loss": 0.5643619913877074,
      "grad_norm": 0.7883075737308247,
      "layer_metrics": {
        "layer_0": {
          "stable_rank": 2.5760507524505623,
          "participation_ratio": 2.447248214828034,
          "effective_rank_90": 2.189643139582978,
          "nuclear_norm_ratio": 2.8336558276956185
        }
      }
    },
    {
      "step": 325,
      "loss": 0.5528968529696463,
      "grad_norm": 0.7769308502134844,
      "layer_metrics": {
        "layer_0": {
          "stable_rank": 2.522322898775665,
          "participation_ratio": 2.3962067538368816,
          "effective_rank_90": 2.143974463959315,
          "nuclear_norm_ratio": 2.7745551886532316
        }
      }
    },
    {
      "step": 330,
      "loss": 0.5417147898277345,
      "grad_norm": 0.7657421673961591,
      "layer_metrics": {
        "layer_0": {
          "stable_rank": 2.6697501663827268,
          "participation_ratio": 2.5362626580635905,
          "effective_rank_90": 2.2692876414253176,
          "nuclear_norm_ratio": 2.9367251830209997
        }
      }
    },
    {
      "step": 335,
      "loss": 0.5308088128085011,
      "grad_norm": 0.7547384172394552,
      "layer_metrics": {
        "layer_0": {
          "stable_rank": 2.5669755428890935,
          "participation_ratio": 2.4386267657446385,
          "effective_rank_90": 2.1819292114557296,
          "nuclear_norm_ratio": 2.823673097178003
        }
      }
    },
    {
      "step": 340,
      "loss": 0.5201721053212897,
      "grad_norm": 0.7439165430753518,
      "layer_metrics": {
        "layer_0": {
          "stable_rank": 2.6278035456829896,
          "participation_ratio": 2.49641336839884,
          "effective_rank_90": 2.233633013830541,
          "nuclear_norm_ratio": 2.890583900251289
        }
      }
    },
    {
      "step": 345,
      "loss": 0.5097980190776663,
      "grad_norm": 0.7332735387581064,
      "layer_metrics": {
        "layer_0": {
          "stable_rank": 2.6423956352717566,
          "participation_ratio": 2.5102758535081686,
          "effective_rank_90": 2.246036289980993,
          "nuclear_norm_ratio": 2.9066351987989325
        }
      }
    },
    {
      "step": 350,
      "loss": 0.49968006993602376,
      "grad_norm": 0.7228064478291953,
      "layer_metrics": {
        "layer_0": {
          "stable_rank": 2.895277742236386,
          "participation_ratio": 2.7505138551245665,
          "effective_rank_90": 2.460986080900928,
          "nuclear_norm_ratio": 3.1848055164600244
        }
      }
    },
    {
      "step": 355,
      "loss": 0.4898119338487812,
      "grad_norm": 0.7125123626960561,
      "layer_metrics": {
        "layer_0": {
          "stable_rank": 2.668306103038426,
          "participation_ratio": 2.5348907978865047,
          "effective_rank_90": 2.268060187582662,
          "nuclear_norm_ratio": 2.9351367133422688
        }
      }
    },
    {
      "step": 360,
      "loss": 0.480187442909649,
      "grad_norm": 0.7023884238244041,
      "layer_metrics": {
        "layer_0": {
          "stable_rank": 2.6605071814796144,
          "participation_ratio": 2.5274818224056337,
          "effective_rank_90": 2.2614311042576722,
          "nuclear_norm_ratio": 2.9265578996275763
        }
      }
    },
    {
      "step": 365,
      "loss": 0.4708005814984866,
      "grad_norm": 0.6924318189438995,
      "layer_metrics": {
        "layer_0": {
          "stable_rank": 2.483987584162562,
          "participation_ratio": 2.3597882049544334,
          "effective_rank_90": 2.1113894465381775,
          "nuclear_norm_ratio": 2.732386342578818
        }
      }
    },
    {
      "step": 370,
      "loss": 0.4616454825213435,
      "grad_norm": 0.682639782266942,
      "layer_metrics": {
        "layer_0": {
          "stable_rank": 2.5861989069253197,
          "participation_ratio": 2.4568889615790535,
          "effective_rank_90": 2.198269070886522,
          "nuclear_norm_ratio": 2.844818797617852
        }
      }
    },
    {
      "step": 375,
      "loss": 0.4527164237433354,
      "grad_norm": 0.6730095937203802,
      "layer_metrics": {
        "layer_0": {
          "stable_rank": 2.456634440972966,
          "participation_ratio": 2.3338027189243173,
          "effective_rank_90": 2.088139274827021,
          "nuclear_norm_ratio": 2.7022978850702626
        }
      }
    },
    {
      "step": 380,
      "loss": 0.44400782421206064,
      "grad_norm": 0.6635385781899167,
      "layer_metrics": {
        "layer_0": {
          "stable_rank": 2.4144560500102448,
          "participation_ratio": 2.2937332475097323,
          "effective_rank_90": 2.052287642508708,
          "nuclear_norm_ratio": 2.6559016550112693
        }
      }
    },
    {
      "step": 385,
      "loss": 0.4355142407693229,
      "grad_norm": 0.6542241047770045,
      "layer_metrics": {
        "layer_0": {
          "stable_rank": 2.2460982158709695,
          "participation_ratio": 2.133793305077421,
          "effective_rank_90": 1.909183483490324,
          "nuclear_norm_ratio": 2.4707080374580666
        }
      }
    },
    {
      "step": 390,
      "loss": 0.42723036464898123,
      "grad_norm": 0.6450635860680252,
      "layer_metrics": {
        "layer_0": {
          "stable_rank": 2.2621910108973196,
          "participation_ratio": 2.1490814603524533,
          "effective_rank_90": 1.9228623592627216,
          "nuclear_norm_ratio": 2.4884101119870516
        }
      }
    },
    {
      "step": 395,
      "loss": 0.4191510181587971,
      "grad_norm": 0.6360544774155451,
      "layer_metrics": {
        "layer_0": {
          "stable_rank": 2.4415134744060105,
          "participation_ratio": 2.31943780068571,
          "effective_rank_90": 2.0752864532451087,
          "nuclear_norm_ratio": 2.6856648218466117
        }
      }
    },
    {
      "step": 400,
      "loss": 0.4112711514442092,
      "grad_norm": 0.6271942762314535,
      "layer_metrics": {
        "layer_0": {
          "stable_rank": 2.4405423473377854,
          "participation_ratio": 2.318515229970896,
          "effective_rank_90": 2.0744609952371174,
          "nuclear_norm_ratio": 2.6845965820715643
        }
      }
    },
    {
      "step": 405,
      "loss": 0.40358583933200953,
      "grad_norm": 0.618480521291783,
      "layer_metrics": {
        "layer_0": {
          "stable_rank": 2.570556047984435,
          "participation_ratio": 2.442028245585213,
          "effective_rank_90": 2.1849726407867696,
          "nuclear_norm_ratio": 2.8276116527828785
        }
      }
    },
    {
      "step": 410,
      "loss": 0.39609027825194976,
      "grad_norm": 0.6099107920530199,
      "layer_metrics": {
        "layer_0": {
          "stable_rank": 2.567286178452777,
          "participation_ratio": 2.4389218695301382,
          "effective_rank_90": 2.1821932516848603,
          "nuclear_norm_ratio": 2.824014796298055
        }
      }
    },
    {
      "step": 415,
      "loss": 0.3887797832343536,
      "grad_norm": 0.601482707979716,
      "layer_metrics": {
        "layer_0": {
          "stable_rank": 2.4631801216380094,
          "participation_ratio": 2.340021115556109,
          "effective_rank_90": 2.0937031033923077,
          "nuclear_norm_ratio": 2.7094981338018105
        }
      }
    },
    {
      "step": 420,
      "loss": 0.3816497849818584,
      "grad_norm": 0.593193927883213,
      "layer_metrics": {
        "layer_0": {
          "stable_rank": 2.3116786346535303,
          "participation_ratio": 2.1960947029208535,
          "effective_rank_90": 1.9649268394555006,
          "nuclear_norm_ratio": 2.5428464981188834
        }
      }
    },
    {
      "step": 425,
      "loss": 0.37469582701345516,
      "grad_norm": 0.5850421492712974,
      "layer_metrics": {
        "layer_0": {
          "stable_rank": 2.3742878168529926,
          "participation_ratio": 2.255573426010343,
          "effective_rank_90": 2.0181446443250435,
          "nuclear_norm_ratio": 2.611716598538292
        }
      }
    },
    {
      "step": 430,
      "loss": 0.367913562879043,
      "grad_norm": 0.5770251077086048,
      "layer_metrics": {
        "layer_0": {
          "stable_rank": 2.3967528135567635,
          "participation_ratio": 2.276915172878925,
          "effective_rank_90": 2.037239891523249,
          "nuclear_norm_ratio": 2.63642809491244
        }
      }
    },
    {
      "step": 435,
      "loss": 0.36129875344275664,
      "grad_norm": 0.5691405761875953,
      "layer_metrics": {
        "layer_0": {
          "stable_rank": 2.3396696480180608,
          "participation_ratio": 2.2226861656171577,
          "effective_rank_90": 1.9887192008153516,
          "nuclear_norm_ratio": 2.573636612819867
        }
      }
    },
    {
      "step": 440,
      "loss": 0.3548472642333679,
      "grad_norm": 0.5613863645099257,
      "layer_metrics": {
        "layer_0": {
          "stable_rank": 2.345058457096075,
          "participation_ratio": 2.2278055342412713,
          "effective_rank_90": 1.9932996885316638,
          "nuclear_norm_ratio": 2.5795643028056827
        }
      }
    },
    {
      "step": 445,
      "loss": 0.3485550628601073,
      "grad_norm": 0.5537603186780473,
      "layer_metrics": {
        "layer_0": {
          "stable_rank": 2.2929136856709467,
          "participation_ratio": 2.178268001387399,
          "effective_rank_90": 1.9489766328203046,
          "nuclear_norm_ratio": 2.5222050542380416
        }
      }
    },
    {
      "step": 450,
      "loss": 0.342418216492288,
      "grad_norm": 0.5462603202968597,
      "layer_metrics": {
        "layer_0": {
          "stable_rank": 2.188075132088486,
          "participation_ratio": 2.0786713754840616,
          "effective_rank_90": 1.859863862275213,
          "nuclear_norm_ratio": 2.4068826452973346
        }
      }
    },
    {
      "step": 455,
      "loss": 0.3364328894011587,
      "grad_norm": 0.5388842859852533,
      "layer_metrics": {
        "layer_0": {
          "stable_rank": 2.318707355173004,
          "participation_ratio": 2.202771987414354,
          "effective_rank_90": 1.9709012518970535,
          "nuclear_norm_ratio": 2.550578090690305
        }
      }
    },
    {
      "step": 460,
      "loss": 0.3305953405624486,
      "grad_norm": 0.5316301667973795,
      "layer_metrics": {
        "layer_0": {
          "stable_rank": 2.6039096889401403,
          "participation_ratio": 2.4737142044931333,
          "effective_rank_90": 2.2133232355991193,
          "nuclear_norm_ratio": 2.8643006578341548
        }
      }
    },
    {
      "step": 465,
      "loss": 0.32490192131810514,
      "grad_norm": 0.5244959476534861,
      "layer_metrics": {
        "layer_0": {
          "stable_rank": 2.5765672539007722,
          "participation_ratio": 2.4477388912057334,
          "effective_rank_90": 2.190082165815656,
          "nuclear_norm_ratio": 2.83422397929085
        }
      }
    },
    {
      "step": 470,
      "loss": 0.3193490730957641,
      "grad_norm": 0.5174796467801592,
      "layer_metrics": {
        "layer_0": {
          "stable_rank": 2.4500748941868022,
          "participation_ratio": 2.3275711494774622,
          "effective_rank_90": 2.082563660058782,
          "nuclear_norm_ratio": 2.6950823836054827
        }
      }
    },
    {
      "step": 475,
      "loss": 0.313933325184526,
      "grad_norm": 0.5105793151598186,
      "layer_metrics": {
        "layer_0": {
          "stable_rank": 2.4803728776342457,
          "participation_ratio": 2.3563542337525334,
          "effective_rank_90": 2.1083169459891087,
          "nuclear_norm_ratio": 2.7284101653976705
        }
      }
    },
    {
      "step": 480,
      "loss": 0.30865129256564877,
      "grad_norm": 0.5037930359893108,
      "layer_metrics": {
        "layer_0": {
          "stable_rank": 2.5708827798648795,
          "participation_ratio": 2.442338640871635,
          "effective_rank_90": 2.1852503628851476,
          "nuclear_norm_ratio": 2.8279710578513675
        }
      }
    },
    {
      "step": 485,
      "loss": 0.3034996737968008,
      "grad_norm": 0.4971189241474522,
      "layer_metrics": {
        "layer_0": {
          "stable_rank": 2.5683733481230546,
          "participation_ratio": 2.4399546807169017,
          "effective_rank_90": 2.1831173459045963,
          "nuclear_norm_ratio": 2.8252106829353605
        }
      }
    },
    {
      "step": 490,
      "loss": 0.29847524894855215,
      "grad_norm": 0.4905551256713715,
      "layer_metrics": {
        "layer_0": {
          "stable_rank": 2.471499543778325,
          "participation_ratio": 2.3479245665894086,
          "effective_rank_90": 2.1007746122115765,
          "nuclear_norm_ratio": 2.7186494981561578
        }
      }
    },
    {
      "step": 495,
      "loss": 0.29357487759181383,
      "grad_norm": 0.4840998172415083,
      "layer_metrics": {
        "layer_0": {
          "stable_rank": 2.5267537504411393,
          "participation_ratio": 2.4004160629190823,
          "effective_rank_90": 2.1477406878749683,
          "nuclear_norm_ratio": 2.7794291254852532
        }
      }
    },
    {
      "step": 500,
      "loss": 0.2887954968349672,
      "grad_norm": 0.47775120567512364,
      "layer_metrics": {
        "layer_0": {
          "stable_rank": 2.654927628525529,
          "participation_ratio": 2.522181247099253,
          "effective_rank_90": 2.2566884842466997,
          "nuclear_norm_ratio": 2.9204203913780824
        }
      }
    },
    {
      "step": 505,
      "loss": 0.2841341194094572,
      "grad_norm": 0.4715075274281827,
      "layer_metrics": {
        "layer_0": {
          "stable_rank": 2.6402337087775165,
          "participation_ratio": 2.5082220233386407,
          "effective_rank_90": 2.244198652460889,
          "nuclear_norm_ratio": 2.9042570796552685
        }
      }
    },
    {
      "step": 510,
      "loss": 0.2795878318026523,
      "grad_norm": 0.46536704810546936,
      "layer_metrics": {
        "layer_0": {
          "stable_rank": 2.584135827482454,
          "participation_ratio": 2.4549290361083314,
          "effective_rank_90": 2.1965154533600857,
          "nuclear_norm_ratio": 2.8425494102306996
        }
      }
    },
    {
      "step": 515,
      "loss": 0.2751537924368037,
      "grad_norm": 0.45932806197879883,
      "layer_metrics": {
        "layer_0": {
          "stable_rank": 2.681017645597705,
          "participation_ratio": 2.5469667633178195,
          "effective_rank_90": 2.278864998758049,
          "nuclear_norm_ratio": 2.9491194101574756
        }
      }
    },
    {
      "step": 520,
      "loss": 0.27082922989296787,
      "grad_norm": 0.4533888915131935,
      "layer_metrics": {
        "layer_0": {
          "stable_rank": 2.8972464721282494,
          "participation_ratio": 2.7523841485218368,
          "effective_rank_90": 2.462659501309012,
          "nuclear_norm_ratio": 3.1869711193410746
        }
      }
    },
    {
      "step": 525,
      "loss": 0.26661144117877833,
      "grad_norm": 0.4475478869008903,
      "layer_metrics": {
        "layer_0": {
          "stable_rank": 2.8843717104915703,
          "participation_ratio": 2.7401531249669917,
          "effective_rank_90": 2.4517159539178346,
          "nuclear_norm_ratio": 3.1728088815407274
        }
      }
    },
    {
      "step": 530,
      "loss": 0.2624977900389881,
      "grad_norm": 0.44180342560304964,
      "layer_metrics": {
        "layer_0": {
          "stable_rank": 2.772137331777219,
          "participation_ratio": 2.633530465188358,
          "effective_rank_90": 2.356316732010636,
          "nuclear_norm_ratio": 3.049351064954941
        }
      }
    },
    {
      "step": 535,
      "loss": 0.25848570530772397,
      "grad_norm": 0.4361539118990403,
      "layer_metrics": {
        "layer_0": {
          "stable_rank": 2.7910643218403948,
          "participation_ratio": 2.651511105748375,
          "effective_rank_90": 2.3724046735643354,
          "nuclear_norm_ratio": 3.0701707540244345
        }
      }
    },
    {
      "step": 540,
      "loss": 0.25457267930142446,
      "grad_norm": 0.4305977764431731,
      "layer_metrics": {
        "layer_0": {
          "stable_rank": 2.7696556671990193,
          "participation_ratio": 2.6311728838390684,
          "effective_rank_90": 2.354207317119166,
          "nuclear_norm_ratio": 3.0466212339189216
        }
      }
    },
    {
      "step": 545,
      "loss": 0.250756266251456,
      "grad_norm": 0.4251334758287615,
      "layer_metrics": {
        "layer_0": {
          "stable_rank": 2.9969606266015663,
          "participation_ratio": 2.8471125952714877,
          "effective_rank_90": 2.547416532611331,
          "nuclear_norm_ratio": 3.2966566892617233
        }
      }
    },
    {
      "step": 550,
      "loss": 0.2470340807754274,
      "grad_norm": 0.4197594921593878,
      "layer_metrics": {
        "layer_0": {
          "stable_rank": 3.169271182906385,
          "participation_ratio": 3.0108076237610657,
          "effective_rank_90": 2.693880505470427,
          "nuclear_norm_ratio": 3.4861983011970237
        }
      }
    },
    {
      "step": 555,
      "loss": 0.24340379638624887,
      "grad_norm": 0.4144743326272552,
      "layer_metrics": {
        "layer_0": {
          "stable_rank": 3.008817846921547,
          "participation_ratio": 2.8583769545754696,
          "effective_rank_90": 2.557495169883315,
          "nuclear_norm_ratio": 3.3096996316137024
        }
      }
    },
    {
      "step": 560,
      "loss": 0.23986314403800132,
      "grad_norm": 0.40927652909850964,
      "layer_metrics": {
        "layer_0": {
          "stable_rank": 3.0570026976490454,
          "participation_ratio": 2.904152562766593,
          "effective_rank_90": 2.5984522930016887,
          "nuclear_norm_ratio": 3.3627029674139504
        }
      }
    },
    {
      "step": 565,
      "loss": 0.23640991070770906,
      "grad_norm": 0.4041646377054151,
      "layer_metrics": {
        "layer_0": {
          "stable_rank": 3.3037988172578734,
          "participation_ratio": 3.1386088763949798,
          "effective_rank_90": 2.8082289946691925,
          "nuclear_norm_ratio": 3.634178698983661
        }
      }
    },
    {
      "step": 570,
      "loss": 0.23304193801212844,
      "grad_norm": 0.39913723844527016,
      "layer_metrics": {
        "layer_0": {
          "stable_rank": 3.1342929357915654,
          "participation_ratio": 2.977578289001987,
          "effective_rank_90": 2.6641489954228303,
          "nuclear_norm_ratio": 3.447722229370722
        }
      }
    },
    {
      "step": 575,
      "loss": 0.2297571208586879,
      "grad_norm": 0.39419293478595363,
      "layer_metrics": {
        "layer_0": {
          "stable_rank": 3.1708011501979585,
          "participation_ratio": 3.0122610926880604,
          "effective_rank_90": 2.6951809776682647,
          "nuclear_norm_ratio": 3.4878812652177547
        }
      }
    },
    {
      "step": 580,
      "loss": 0.22655340612973662,
      "grad_norm": 0.38933035327799015,
      "layer_metrics": {
        "layer_0": {
          "stable_rank": 3.023989163308507,
          "participation_ratio": 2.8727897051430813,
          "effective_rank_90": 2.570390788812231,
          "nuclear_norm_ratio": 3.326388079639358
        }
      }
    },
    {
      "step": 585,
      "loss": 0.2234287913992793,
      "grad_norm": 0.3845481431730272,
      "layer_metrics": {
        "layer_0": {
          "stable_rank": 2.7802718649799245,
          "participation_ratio": 2.641258271730928,
          "effective_rank_90": 2.3632310852329357,
          "nuclear_norm_ratio": 3.0582990514779174
        }
      }
    },
    {
      "step": 590,
      "loss": 0.22038132368139446,
      "grad_norm": 0.3798449760486188,
      "layer_metrics": {
        "layer_0": {
          "stable_rank": 2.821079749062397,
          "participation_ratio": 2.680025761609277,
          "effective_rank_90": 2.3979177867030375,
          "nuclear_norm_ratio": 3.103187723968637
        }
      }
    },
    {
      "step": 595,
      "loss": 0.21740909820955512,
      "grad_norm": 0.37521954543921077,
      "layer_metrics": {
        "layer_0": {
          "stable_rank": 2.649760942993327,
          "participation_ratio": 2.5172728958436608,
          "effective_rank_90": 2.252296801544328,
          "nuclear_norm_ratio": 2.91473703729266
        }
      }
    },
    {
      "step": 600,
      "loss": 0.21451025724608708,
      "grad_norm": 0.3706705664732254,
      "layer_metrics": {
        "layer_0": {
          "stable_rank": 2.6031115528474285,
          "participation_ratio": 2.472955975205057,
          "effective_rank_90": 2.212644819920314,
          "nuclear_norm_ratio": 2.8634227081321715
        }
      }
    },
    {
      "step": 605,
      "loss": 0.21168298892102294,
      "grad_norm": 0.3661967755161437,
      "layer_metrics": {
        "layer_0": {
          "stable_rank": 2.631874531015887,
          "participation_ratio": 2.500280804465093,
          "effective_rank_90": 2.237093351363504,
          "nuclear_norm_ratio": 2.895061984117476
        }
      }
    },
    {
      "step": 610,
      "loss": 0.20892552609962411,
      "grad_norm": 0.36179692981948863,
      "layer_metrics": {
        "layer_0": {
          "stable_rank": 2.603344243350855,
          "participation_ratio": 2.473177031183312,
          "effective_rank_90": 2.2128426068482265,
          "nuclear_norm_ratio": 2.8636786676859405
        }
      }
    },
    {
      "step": 615,
      "loss": 0.2062361452778642,
      "grad_norm": 0.3574698071756085,
      "layer_metrics": {
        "layer_0": {
          "stable_rank": 2.6848247753267915,
          "participation_ratio": 2.5505835365604517,
          "effective_rank_90": 2.282101059027773,
          "nuclear_norm_ratio": 2.953307252859471
        }
      }
    },
    {
      "step": 620,
      "loss": 0.20361316550518294,
      "grad_norm": 0.3532142055781671,
      "layer_metrics": {
        "layer_0": {
          "stable_rank": 2.9659091641654474,
          "participation_ratio": 2.817613705957175,
          "effective_rank_90": 2.52102278954063,
          "nuclear_norm_ratio": 3.2625000805819924
        }
      }
    },
    {
      "step": 625,
      "loss": 0.20105494733383705,
      "grad_norm": 0.34902894288824593,
      "layer_metrics": {
        "layer_0": {
          "stable_rank": 2.8985843781487226,
          "participation_ratio": 2.7536551592412866,
          "effective_rank_90": 2.463796721426414,
          "nuclear_norm_ratio": 3.188442815963595
        }
      }
    },
    {
      "step": 630,
      "loss": 0.19855989179419242,
      "grad_norm": 0.3449128565059638,
      "layer_metrics": {
        "layer_0": {
          "stable_rank": 2.9616387322166364,
          "participation_ratio": 2.8135567956058045,
          "effective_rank_90": 2.5173929223841407,
          "nuclear_norm_ratio": 3.2578026054383002
        }
      }
    },
    {
      "step": 635,
      "loss": 0.19612643939531582,
      "grad_norm": 0.3408648030475254,
      "layer_metrics": {
        "layer_0": {
          "stable_rank": 2.8586011418637383,
          "participation_ratio": 2.7156710847705514,
          "effective_rank_90": 2.4298109705841773,
          "nuclear_norm_ratio": 3.1444612560501124
        }
      }
    },
    {
      "step": 640,
      "loss": 0.19375306915024226,
      "grad_norm": 0.3368836580276074,
      "layer_metrics": {
        "layer_0": {
          "stable_rank": 2.936255739935495,
          "participation_ratio": 2.78944295293872,
          "effective_rank_90": 2.495817378945171,
          "nuclear_norm_ratio": 3.2298813139290448
        }
      }
    },
    {
      "step": 645,
      "loss": 0.191438297625309,
      "grad_norm": 0.3329683155469939,
      "layer_metrics": {
        "layer_0": {
          "stable_rank": 2.8152006091830257,
          "participation_ratio": 2.6744405787238743,
          "effective_rank_90": 2.392920517805572,
          "nuclear_norm_ratio": 3.0967206701013286
        }
      }
    },
    {
      "step": 650,
      "loss": 0.18918067801296062,
      "grad_norm": 0.32911768798537544,
      "layer_metrics": {
        "layer_0": {
          "stable_rank": 2.755120932168403,
          "participation_ratio": 2.617364885559983,
          "effective_rank_90": 2.3418527923431425,
          "nuclear_norm_ratio": 3.0306330253852436
        }
      }
    },
    {
      "step": 655,
      "loss": 0.1869787992274477,
      "grad_norm": 0.32533070569922495,
      "layer_metrics": {
        "layer_0": {
          "stable_rank": 2.737946626213663,
          "participation_ratio": 2.60104929490298,
          "effective_rank_90": 2.3272546322816137,
          "nuclear_norm_ratio": 3.01174128883503
        }
      }
    },
    {
      "step": 660,
      "loss": 0.184831285022852,
      "grad_norm": 0.3216063167246678,
      "layer_metrics": {
        "layer_0": {
          "stable_rank": 2.6410147070775043,
          "participation_ratio": 2.508963971723629,
          "effective_rank_90": 2.2448625010158785,
          "nuclear_norm_ratio": 2.905116177785255
        }
      }
    },
    {
      "step": 665,
      "loss": 0.1827367931328882,
      "grad_norm": 0.3179434864852628,
      "layer_metrics": {
        "layer_0": {
          "stable_rank": 2.6121242126533155,
          "participation_ratio": 2.4815180020206498,
          "effective_rank_90": 2.2203055807553183,
          "nuclear_norm_ratio": 2.8733366339186475
        }
      }
    },
    {
      "step": 670,
      "loss": 0.18069401443194355,
      "grad_norm": 0.3143411975046135,
      "layer_metrics": {
        "layer_0": {
          "stable_rank": 2.7805509792580687,
          "participation_ratio": 2.641523430295165,
          "effective_rank_90": 2.3634683323693584,
          "nuclear_norm_ratio": 3.058606077183876
        }
      }
    },
    {
      "step": 675,
      "loss": 0.17870167211683186,
      "grad_norm": 0.31079844912372867,
      "layer_metrics": {
        "layer_0": {
          "stable_rank": 2.960090601808165,
          "participation_ratio": 2.812086071717757,
          "effective_rank_90": 2.5160770115369404,
          "nuclear_norm_ratio": 3.256099661988982
        }
      }
    },
    {
      "step": 680,
      "loss": 0.17675852090875,
      "grad_norm": 0.3073142572230557,
      "layer_metrics": {
        "layer_0": {
          "stable_rank": 3.0158623945598655,
          "participation_ratio": 2.865069274831872,
          "effective_rank_90": 2.5634830353758855,
          "nuclear_norm_ratio": 3.3174486340158524
        }
      }
    },
    {
      "step": 685,
      "loss": 0.17486334627493788,
      "grad_norm": 0.3038876539491074,
      "layer_metrics": {
        "layer_0": {
          "stable_rank": 3.2669814044344108,
          "participation_ratio": 3.10363233421269,
          "effective_rank_90": 2.776934193769249,
          "nuclear_norm_ratio": 3.593679544877852
        }
      }
    },
    {
      "step": 690,
      "loss": 0.17301496366955627,
      "grad_norm": 0.3005176874456075,
      "layer_metrics": {
        "layer_0": {
          "stable_rank": 3.406519461169035,
          "participation_ratio": 3.2361934881105827,
          "effective_rank_90": 2.8955415419936794,
          "nuclear_norm_ratio": 3.7471714072859386
        }
      }
    },
    {
      "step": 695,
      "loss": 0.1712122177933068,
      "grad_norm": 0.2972034215890802,
      "layer_metrics": {
        "layer_0": {
          "stable_rank": 3.4184776856409953,
          "participation_ratio": 3.2475538013589453,
          "effective_rank_90": 2.905706032794846,
          "nuclear_norm_ratio": 3.7603254542050952
        }
      }
    },
    {
      "step": 700,
      "loss": 0.16945398187133254,
      "grad_norm": 0.2939439357288101,
      "layer_metrics": {
        "layer_0": {
          "stable_rank": 3.5833029291295007,
          "participation_ratio": 3.4041377826730255,
          "effective_rank_90": 3.0458074897600755,
          "nuclear_norm_ratio": 3.941633222042451
        }
      }
    },
    {
      "step": 705,
      "loss": 0.16773915694894675,
      "grad_norm": 0.29073832443109926,
      "layer_metrics": {
        "layer_0": {
          "stable_rank": 3.711261522785471,
          "participation_ratio": 3.525698446646197,
          "effective_rank_90": 3.15457229436765,
          "nuclear_norm_ratio": 4.082387675064019
        }
      }
    },
    {
      "step": 710,
      "loss": 0.16606667120475072,
      "grad_norm": 0.2875856972277525,
      "layer_metrics": {
        "layer_0": {
          "stable_rank": 3.7845354314916353,
          "participation_ratio": 3.595308659917053,
          "effective_rank_90": 3.21685511676789,
          "nuclear_norm_ratio": 4.1629889746407995
        }
      }
    },
    {
      "step": 715,
      "loss": 0.16443547928071017,
      "grad_norm": 0.28448517836871956,
      "layer_metrics": {
        "layer_0": {
          "stable_rank": 3.6977796953915374,
          "participation_ratio": 3.5128907106219605,
          "effective_rank_90": 3.1431127410828066,
          "nuclear_norm_ratio": 4.067557664930692
        }
      }
    },
    {
      "step": 720,
      "loss": 0.16284456162877287,
      "grad_norm": 0.281435906578825,
      "layer_metrics": {
        "layer_0": {
          "stable_rank": 3.626463026864441,
          "participation_ratio": 3.445139875521219,
          "effective_rank_90": 3.0824935728347747,
          "nuclear_norm_ratio": 3.9891093295508857
        }
      }
    },
    {
      "step": 725,
      "loss": 0.1612929238736176,
      "grad_norm": 0.2784370348185202,
      "layer_metrics": {
        "layer_0": {
          "stable_rank": 3.5355564387085656,
          "participation_ratio": 3.358778616773137,
          "effective_rank_90": 3.005222972902281,
          "nuclear_norm_ratio": 3.8891120825794223
        }
      }
    },
    {
      "step": 730,
      "loss": 0.1597795961911373,
      "grad_norm": 0.2754877300485887,
      "layer_metrics": {
        "layer_0": {
          "stable_rank": 3.4692230595310902,
          "participation_ratio": 3.2957619065545356,
          "effective_rank_90": 2.948839600601427,
          "nuclear_norm_ratio": 3.8161453654841995
        }
      }
    },
    {
      "step": 735,
      "loss": 0.15830363270226738,
      "grad_norm": 0.272587172998741,
      "layer_metrics": {
        "layer_0": {
          "stable_rank": 3.4637691975940763,
          "participation_ratio": 3.2905807377143725,
          "effective_rank_90": 2.944203817954965,
          "nuclear_norm_ratio": 3.8101461173534843
        }
      }
    },
    {
      "step": 740,
      "loss": 0.1568641108817806,
      "grad_norm": 0.2697345579400348,
      "layer_metrics": {
        "layer_0": {
          "stable_rank": 3.589176686111899,
          "participation_ratio": 3.409717851806304,
          "effective_rank_90": 3.050800183195114,
          "nuclear_norm_ratio": 3.9480943547230893
        }
      }
    },
    {
      "step": 745,
      "loss": 0.1554601309816788,
      "grad_norm": 0.2669290924610556,
      "layer_metrics": {
        "layer_0": {
          "stable_rank": 3.655084362506826,
          "participation_ratio": 3.4723301443814845,
          "effective_rank_90": 3.106821708130802,
          "nuclear_norm_ratio": 4.020592798757509
        }
      }
    },
    {
      "step": 750,
      "loss": 0.15409081546882095,
      "grad_norm": 0.2641699972477976,
      "layer_metrics": {
        "layer_0": {
          "stable_rank": 3.7946225155154436,
          "participation_ratio": 3.604891389739671,
          "effective_rank_90": 3.225429138188127,
          "nuclear_norm_ratio": 4.174084767066988
        }
      }
    },
    {
      "step": 755,
      "loss": 0.15275530847643654,
      "grad_norm": 0.26145650586718244,
      "layer_metrics": {
        "layer_0": {
          "stable_rank": 3.7017397485817685,
          "participation_ratio": 3.5166527611526797,
          "effective_rank_90": 3.146478786294503,
          "nuclear_norm_ratio": 4.071913723439946
        }
      }
    },
    {
      "step": 760,
      "loss": 0.15145277526918088,
      "grad_norm": 0.2587878645541565,
      "layer_metrics": {
        "layer_0": {
          "stable_rank": 3.432849490150329,
          "participation_ratio": 3.261207015642812,
          "effective_rank_90": 2.917922066627779,
          "nuclear_norm_ratio": 3.776134439165362
        }
      }
    },
    {
      "step": 765,
      "loss": 0.15018240172139835,
      "grad_norm": 0.25616333200230634,
      "layer_metrics": {
        "layer_0": {
          "stable_rank": 3.5986370328108386,
          "participation_ratio": 3.4187051811702966,
          "effective_rank_90": 3.058841477889213,
          "nuclear_norm_ratio": 3.958500736091923
        }
      }
    },
    {
      "step": 770,
      "loss": 0.1489433938082675,
      "grad_norm": 0.25358217915793607,
      "layer_metrics": {
        "layer_0": {
          "stable_rank": 3.624660173836133,
          "participation_ratio": 3.443427165144326,
          "effective_rank_90": 3.080961147760713,
          "nuclear_norm_ratio": 3.9871261912197467
        }
      }
    },
    {
      "step": 775,
      "loss": 0.14773497710950942,
      "grad_norm": 0.25104368901754753,
      "layer_metrics": {
        "layer_0": {
          "stable_rank": 3.6955640500041227,
          "participation_ratio": 3.510785847503916,
          "effective_rank_90": 3.141229442503504,
          "nuclear_norm_ratio": 4.065120455004536
        }
      }
    },
    {
      "step": 780,
      "loss": 0.1465563963253501,
      "grad_norm": 0.24854715642866776,
      "layer_metrics": {
        "layer_0": {
          "stable_rank": 3.574023311463796,
          "participation_ratio": 3.395322145890606,
          "effective_rank_90": 3.0379198147442263,
          "nuclear_norm_ratio": 3.931425642610176
        }
      }
    },
    {
      "step": 785,
      "loss": 0.1454069148044334,
      "grad_norm": 0.24609188789396913,
      "layer_metrics": {
        "layer_0": {
          "stable_rank": 3.361575170547203,
          "participation_ratio": 3.1934964120198424,
          "effective_rank_90": 2.8573388949651224,
          "nuclear_norm_ratio": 3.697732687601923
        }
      }
    },
    {
      "step": 790,
      "loss": 0.14428581408338992,
      "grad_norm": 0.24367720137862658,
      "layer_metrics": {
        "layer_0": {
          "stable_rank": 3.324570178893332,
          "participation_ratio": 3.1583416699486655,
          "effective_rank_90": 2.825884652059332,
          "nuclear_norm_ratio": 3.6570271967826655
        }
      }
    },
    {
      "step": 795,
      "loss": 0.14319239343777412,
      "grad_norm": 0.2413024261208592,
      "layer_metrics": {
        "layer_0": {
          "stable_rank": 3.3546658556571876,
          "participation_ratio": 3.186932562874328,
          "effective_rank_90": 2.8514659773086093,
          "nuclear_norm_ratio": 3.6901324412229064
        }
      }
    },
    {
      "step": 800,
      "loss": 0.14212596944408862,
      "grad_norm": 0.2389669024456031,
      "layer_metrics": {
        "layer_0": {
          "stable_rank": 3.2402472869225467,
          "participation_ratio": 3.0782349225764194,
          "effective_rank_90": 2.7542101938841648,
          "nuclear_norm_ratio": 3.564272015614802
        }
      }
    },
    {
      "step": 805,
      "loss": 0.14108587555262228,
      "grad_norm": 0.23666998158126418,
      "layer_metrics": {
        "layer_0": {
          "stable_rank": 3.2228994309259162,
          "participation_ratio": 3.06175445937962,
          "effective_rank_90": 2.7394645162870286,
          "nuclear_norm_ratio": 3.5451893740185083
        }
      }
    },
    {
      "step": 810,
      "loss": 0.1400714616708351,
      "grad_norm": 0.23441102547949952,
      "layer_metrics": {
        "layer_0": {
          "stable_rank": 3.2433866273029417,
          "participation_ratio": 3.0812172959377944,
          "effective_rank_90": 2.7568786332075,
          "nuclear_norm_ratio": 3.5677252900332364
        }
      }
    },
    {
      "step": 815,
      "loss": 0.13908209375702885,
      "grad_norm": 0.23218940663797785,
      "layer_metrics": {
        "layer_0": {
          "stable_rank": 3.1452757326063936,
          "participation_ratio": 2.9880119459760737,
          "effective_rank_90": 2.6734843727154343,
          "nuclear_norm_ratio": 3.4598033058670334
        }
      }
    },
    {
      "step": 820,
      "loss": 0.1381171534240509,
      "grad_norm": 0.23000450792606908,
      "layer_metrics": {
        "layer_0": {
          "stable_rank": 3.241306118763401,
          "participation_ratio": 3.079240812825231,
          "effective_rank_90": 2.755110200948891,
          "nuclear_norm_ratio": 3.5654367306397416
        }
      }
    },
    {
      "step": 825,
      "loss": 0.13717603755278152,
      "grad_norm": 0.22785572241341515,
      "layer_metrics": {
        "layer_0": {
          "stable_rank": 3.424189623143296,
          "participation_ratio": 3.252980141986131,
          "effective_rank_90": 2.9105611796718014,
          "nuclear_norm_ratio": 3.7666085854576257
        }
      }
    },
    {
      "step": 830,
      "loss": 0.13625815791516532,
      "grad_norm": 0.22574245320133457,
      "layer_metrics": {
        "layer_0": {
          "stable_rank": 3.364972184057321,
          "participation_ratio": 3.1967235748544547,
          "effective_rank_90": 2.8602263564487225,
          "nuclear_norm_ratio": 3.701469402463053
        }
      }
    },
    {
      "step": 835,
      "loss": 0.13536294080654931,
      "grad_norm": 0.22366411325701321,
      "layer_metrics": {
        "layer_0": {
          "stable_rank": 3.45619404071924,
          "participation_ratio": 3.2833843386832777,
          "effective_rank_90": 2.9377649346113537,
          "nuclear_norm_ratio": 3.8018134447911645
        }
      }
    },
    {
      "step": 840,
      "loss": 0.13448982668709872,
      "grad_norm": 0.22162012525043595,
      "layer_metrics": {
        "layer_0": {
          "stable_rank": 3.7197226917863806,
          "participation_ratio": 3.5337365571970616,
          "effective_rank_90": 3.1617642880184236,
          "nuclear_norm_ratio": 4.091694960965019
        }
      }
    },
    {
      "step": 845,
      "loss": 0.13363826983206673,
      "grad_norm": 0.21960992139401342,
      "layer_metrics": {
        "layer_0": {
          "stable_rank": 3.690694278479301,
          "participation_ratio": 3.506159564555336,
          "effective_rank_90": 3.137090136707406,
          "nuclear_norm_ratio": 4.059763706327232
        }
      }
    },
    {
      "step": 850,
      "loss": 0.13280773799069828,
      "grad_norm": 0.21763294328485977,
      "layer_metrics": {
        "layer_0": {
          "stable_rank": 3.8117257362610752,
          "participation_ratio": 3.6211394494480214,
          "effective_rank_90": 3.239966875821914,
          "nuclear_norm_ratio": 4.192898309887183
        }
      }
    },
    {
      "step": 855,
      "loss": 0.13199771205355654,
      "grad_norm": 0.21568864174967692,
      "layer_metrics": {
        "layer_0": {
          "stable_rank": 3.9080026170172135,
          "participation_ratio": 3.7126024861663525,
          "effective_rank_90": 3.3218022244646312,
          "nuclear_norm_ratio": 4.298802878718935
        }
      }
    },
    {
      "step": 860,
      "loss": 0.13120768572806216,
      "grad_norm": 0.21377647669220304,
      "layer_metrics": {
        "layer_0": {
          "stable_rank": 3.9874146939195585,
          "participation_ratio": 3.7880439592235806,
          "effective_rank_90": 3.389302489831625,
          "nuclear_norm_ratio": 4.386156163311514
        }
      }
    },
    {
      "step": 865,
      "loss": 0.13043716522204413,
      "grad_norm": 0.21189591694318233,
      "layer_metrics": {
        "layer_0": {
          "stable_rank": 4.071114612092247,
          "participation_ratio": 3.8675588814876343,
          "effective_rank_90": 3.4604474202784097,
          "nuclear_norm_ratio": 4.478226073301472
        }
      }
    },
    {
      "step": 870,
      "loss": 0.12968566893510372,
      "grad_norm": 0.21004644011281448,
      "layer_metrics": {
        "layer_0": {
          "stable_rank": 4.069484083643983,
          "participation_ratio": 3.866009879461784,
          "effective_rank_90": 3.4590614710973857,
          "nuclear_norm_ratio": 4.4764324920083824
        }
      }
    },
    {
      "step": 875,
      "loss": 0.1289527271575982,
      "grad_norm": 0.20822753244564324,
      "layer_metrics": {
        "layer_0": {
          "stable_rank": 4.199968298322671,
          "participation_ratio": 3.989969883406537,
          "effective_rank_90": 3.56997305357427,
          "nuclear_norm_ratio": 4.619965128154938
        }
      }
    },
    {
      "step": 880,
      "loss": 0.12823788177705742,
      "grad_norm": 0.20643868867784304,
      "layer_metrics": {
        "layer_0": {
          "stable_rank": 4.310332762467136,
          "participation_ratio": 4.0948161243437795,
          "effective_rank_90": 3.663782848097066,
          "nuclear_norm_ratio": 4.74136603871385
        }
      }
    },
    {
      "step": 885,
      "loss": 0.12754068599184834,
      "grad_norm": 0.20467941189686478,
      "layer_metrics": {
        "layer_0": {
          "stable_rank": 4.357338440815906,
          "participation_ratio": 4.13947151877511,
          "effective_rank_90": 3.70373767469352,
          "nuclear_norm_ratio": 4.793072284897497
        }
      }
    },
    {
      "step": 890,
      "loss": 0.12686070403190952,
      "grad_norm": 0.20294921340340152,
      "layer_metrics": {
        "layer_0": {
          "stable_rank": 4.300777867033106,
          "participation_ratio": 4.08573897368145,
          "effective_rank_90": 3.65566118697814,
          "nuclear_norm_ratio": 4.730855653736417
        }
      }
    },
    {
      "step": 895,
      "loss": 0.12619751088638076,
      "grad_norm": 0.20124761257563525,
      "layer_metrics": {
        "layer_0": {
          "stable_rank": 4.1916417492843685,
          "participation_ratio": 3.98205966182015,
          "effective_rank_90": 3.5628954868917133,
          "nuclear_norm_ratio": 4.610805924212806
        }
      }
    },
    {
      "step": 900,
      "loss": 0.1255506920379573,
      "grad_norm": 0.19957413673572788,
      "layer_metrics": {
        "layer_0": {
          "stable_rank": 4.375229233684913,
          "participation_ratio": 4.156467772000667,
          "effective_rank_90": 3.718944848632176,
          "nuclear_norm_ratio": 4.812752157053405
        }
      }
    },
    {
      "step": 905,
      "loss": 0.12491984320380314,
      "grad_norm": 0.19792832101851884,
      "layer_metrics": {
        "layer_0": {
          "stable_rank": 4.3752362850681505,
          "participation_ratio": 4.156474470814743,
          "effective_rank_90": 3.718950842307928,
          "nuclear_norm_ratio": 4.812759913574966
        }
      }
    },
    {
      "step": 910,
      "loss": 0.12430457008286111,
      "grad_norm": 0.1963097082423928,
      "layer_metrics": {
        "layer_0": {
          "stable_rank": 4.478819454783026,
          "participation_ratio": 4.254878482043875,
          "effective_rank_90": 3.806996536565572,
          "nuclear_norm_ratio": 4.926701400261329
        }
      }
    },
    {
      "step": 915,
      "loss": 0.12370448810940171,
      "grad_norm": 0.19471784878228188,
      "layer_metrics": {
        "layer_0": {
          "stable_rank": 4.350450062991451,
          "participation_ratio": 4.132927559841878,
          "effective_rank_90": 3.697882553542733,
          "nuclear_norm_ratio": 4.785495069290596
        }
      }
    },
    {
      "step": 920,
      "loss": 0.12311922221265725,
      "grad_norm": 0.19315230044476683,
      "layer_metrics": {
        "layer_0": {
          "stable_rank": 4.124519923532352,
          "participation_ratio": 3.9182939273557342,
          "effective_rank_90": 3.505841935002499,
          "nuclear_norm_ratio": 4.536971915885588
        }
      }
    },
    {
      "step": 925,
      "loss": 0.1225484065823902,
      "grad_norm": 0.19161262834524295,
      "layer_metrics": {
        "layer_0": {
          "stable_rank": 4.165131678152756,
          "participation_ratio": 3.956875094245118,
          "effective_rank_90": 3.5403619264298425,
          "nuclear_norm_ratio": 4.5816448459680315
        }
      }
    },
    {
      "step": 930,
      "loss": 0.12199168444025006,
      "grad_norm": 0.1900984047871156,
      "layer_metrics": {
        "layer_0": {
          "stable_rank": 3.9897924830705738,
          "participation_ratio": 3.790302858917045,
          "effective_rank_90": 3.3913236106099878,
          "nuclear_norm_ratio": 4.3887717313776315
        }
      }
    },
    {
      "step": 935,
      "loss": 0.12144870781677515,
      "grad_norm": 0.18860920914299317,
      "layer_metrics": {
        "layer_0": {
          "stable_rank": 4.1204762039246585,
          "participation_ratio": 3.9144523937284252,
          "effective_rank_90": 3.5024047733359596,
          "nuclear_norm_ratio": 4.532523824317125
        }
      }
    },
    {
      "step": 940,
      "loss": 0.12091913733390038,
      "grad_norm": 0.18714462773784327,
      "layer_metrics": {
        "layer_0": {
          "stable_rank": 4.183565414740079,
          "participation_ratio": 3.9743871440030754,
          "effective_rank_90": 3.5560306025290673,
          "nuclear_norm_ratio": 4.601921956214087
        }
      }
    },
    {
      "step": 945,
      "loss": 0.120402641992835,
      "grad_norm": 0.18570425373408037,
      "layer_metrics": {
        "layer_0": {
          "stable_rank": 4.063940058970718,
          "participation_ratio": 3.860743056022182,
          "effective_rank_90": 3.45434905012511,
          "nuclear_norm_ratio": 4.47033406486779
        }
      }
    },
    {
      "step": 950,
      "loss": 0.11989889896717747,
      "grad_norm": 0.1842876870185528,
      "layer_metrics": {
        "layer_0": {
          "stable_rank": 3.951960009657035,
          "participation_ratio": 3.754362009174183,
          "effective_rank_90": 3.3591660082084798,
          "nuclear_norm_ratio": 4.347156010622738
        }
      }
    },
    {
      "step": 955,
      "loss": 0.11940759340113852,
      "grad_norm": 0.1828945340913976,
      "layer_metrics": {
        "layer_0": {
          "stable_rank": 3.9728738253642364,
          "participation_ratio": 3.7742301340960243,
          "effective_rank_90": 3.376942751559601,
          "nuclear_norm_ratio": 4.370161207900661
        }
      }
    },
    {
      "step": 960,
      "loss": 0.11892841821274608,
      "grad_norm": 0.18152440795673241,
      "layer_metrics": {
        "layer_0": {
          "stable_rank": 3.939192858055862,
          "participation_ratio": 3.742233215153069,
          "effective_rank_90": 3.3483139293474826,
          "nuclear_norm_ratio": 4.333112143861449
        }
      }
    },
    {
      "step": 965,
      "loss": 0.11846107390190885,
      "grad_norm": 0.18017692801515428,
      "layer_metrics": {
        "layer_0": {
          "stable_rank": 4.126914931657547,
          "participation_ratio": 3.9205691850746693,
          "effective_rank_90": 3.5078776919089147,
          "nuclear_norm_ratio": 4.539606424823302
        }
      }
    },
    {
      "step": 970,
      "loss": 0.11800526836321928,
      "grad_norm": 0.17885171995801497,
      "layer_metrics": {
        "layer_0": {
          "stable_rank": 4.221731804932551,
          "participation_ratio": 4.0106452146859235,
          "effective_rank_90": 3.588472034192668,
          "nuclear_norm_ratio": 4.643904985425807
        }
      }
    },
    {
      "step": 975,
      "loss": 0.11756071670337792,
      "grad_norm": 0.17754841566344404,
      "layer_metrics": {
        "layer_0": {
          "stable_rank": 4.329141731935619,
          "participation_ratio": 4.112684645338837,
          "effective_rank_90": 3.6797704721452758,
          "nuclear_norm_ratio": 4.762055905129181
        }
      }
    },
    {
      "step": 980,
      "loss": 0.11712714106312598,
      "grad_norm": 0.1762666530940904,
      "layer_metrics": {
        "layer_0": {
          "stable_rank": 4.406000616357221,
          "participation_ratio": 4.18570058553936,
          "effective_rank_90": 3.7451005239036377,
          "nuclear_norm_ratio": 4.846600677992943
        }
      }
    },
    {
      "step": 985,
      "loss": 0.11670427044357426,
      "grad_norm": 0.17500607619655406,
      "layer_metrics": {
        "layer_0": {
          "stable_rank": 4.3691336724378065,
          "participation_ratio": 4.150676988815916,
          "effective_rank_90": 3.7137636215721352,
          "nuclear_norm_ratio": 4.806047039681587
        }
      }
    },
    {
      "step": 990,
      "loss": 0.11629184053681987,
      "grad_norm": 0.17376633480248002,
      "layer_metrics": {
        "layer_0": {
          "stable_rank": 4.386800299951724,
          "participation_ratio": 4.167460284954138,
          "effective_rank_90": 3.728780254958965,
          "nuclear_norm_ratio": 4.825480329946897
        }
      }
    },
    {
      "step": 995,
      "loss": 0.11588959356074544,
      "grad_norm": 0.1725470845312872,
      "layer_metrics": {
        "layer_0": {
          "stable_rank": 4.438400858537914,
          "participation_ratio": 4.2164808156110185,
          "effective_rank_90": 3.772640729757227,
          "nuclear_norm_ratio": 4.882240944391706
        }
      }
    }
  ],
  "final_accuracy": 0.9343693090597818,
  "num_steps": 1000,
  "measurement_interval": 5
}